odoo/addons/account_move_tier_validation_forward/README.rst
odoo/addons/account_move_tier_validation_forward/__init__.py
odoo/addons/account_move_tier_validation_forward/__manifest__.py
odoo/addons/account_move_tier_validation_forward/i18n/account_move_tier_validation_forward.pot
odoo/addons/account_move_tier_validation_forward/readme/CONFIGURE.rst
odoo/addons/account_move_tier_validation_forward/readme/CONTRIBUTORS.rst
odoo/addons/account_move_tier_validation_forward/readme/DESCRIPTION.rst
odoo/addons/account_move_tier_validation_forward/readme/INSTALL.rst
odoo/addons/account_move_tier_validation_forward/static/description/icon.png
odoo/addons/account_move_tier_validation_forward/static/description/index.html
odoo/addons/account_move_tier_validation_forward/views/account_move_view.xml
odoo13_addon_account_move_tier_validation_forward-13.0.1.0.1.dev4.dist-info/METADATA
odoo13_addon_account_move_tier_validation_forward-13.0.1.0.1.dev4.dist-info/WHEEL
odoo13_addon_account_move_tier_validation_forward-13.0.1.0.1.dev4.dist-info/top_level.txt
odoo13_addon_account_move_tier_validation_forward-13.0.1.0.1.dev4.dist-info/RECORD
